{
  "ingredients": [
    {
      "id": "oats",
      "quantity": "240 g",
      "approxAmountDescription": "2 cup"
    },
    {
      "id": "salt",
      "quantity": "4 g"
    },
    {
      "id": "groundnut-oil",
      "quantity": "2 tsp"
    },
    {
      "id": "carrot",
      "quantity": "50 g"
    },
    {
      "id": "onion",
      "quantity": "90 g"
    },
    {
      "id": "beans",
      "quantity": "30 g"
    },
    {
      "id": "ginger",
      "quantity": "5 g"
    },
    {
      "id": "green-chili",
      "quantity": "5 g"
    },
    {
      "id": "lemon-juice",
      "quantity": "5 g"
    },
    {
      "id": "coriander",
      "quantity": "5 g"
    },
    {
      "id": "green-peas",
      "quantity": "20 g"
    }
  ],

  "totalWeightInGrams": 1081,
  "oneCupWeightInGramsAfterCooking": 260,
  "numberOfPeopleWhoCanBeServed": 4,
  "instructions": [],
  "tags": []
}


